Workbook

Sheet Dashboard
B2: Kết quả bán hàng và đối soát doanh thu · Nexa Home
B3: Nguồn: Nexa_Sales_P1_Dataset.xlsx, finance_revenue.xlsx · dữ liệu đến 20/02/2021 · USD, chưa VAT · chỉ đơn COMPLETED, đã loại dòng trùng · Δ = Finance − dữ liệu đơn · không gồm bút toán HQ-ADJ
B5: Tháng báo cáo | C5: 12/2020 | E5: Kênh bán | F5: Tất cả | H5: ← ô màu vàng: chọn tháng và kênh từ danh sách; mọi số, câu và biểu đồ tự cập nhật
B6: tham số tính (không sửa): kênh · tháng · tháng trước · cùng kỳ · ngưỡng USD · ngưỡng % | C6: =IF(F5="Cửa hàng","POS",IF(F5="Online","ONLINE","*")) | D6: =INDEX(Calc!$B$2:$B$100,MATCH(C5,Calc!$A$2:$A$100,0)) | E6: =IF(MOD(D6,100)=1,D6-89,D6-1) | F6: =D6-100 | G6: 200 | H6: 0.01
B8: ĐIỂM CHÍNH
B9: =IFERROR("Net Revenue "&C5&" đạt "&FIXED(C17/1000,1)&" nghìn USD — "&IF(E17>=0,"+","−")&FIXED(ABS(E17)*100,1)&"%"&" so với tháng trước, "&IF(G17>=0,"+","−")&FIXED(ABS(G17)*100,1)&"%"&" so với cùng kỳ năm trước.","Chọn tháng có dữ liệu.")
B10: =IFERROR("Biến động so với cùng kỳ đến chủ yếu từ "&IF(ABS(LN(1+G18))>=ABS(LN(1+G19)),"số đơn (","giá trị mỗi đơn (AOV ")&IF(ABS(LN(1+G18))>=ABS(LN(1+G19)),IF(G18>=0,"+","−")&FIXED(ABS(G18)*100,1)&"%",IF(G19>=0,"+","−")&FIXED(ABS(G19)*100,1)&"%")&"); "&IF(ABS(LN(1+G18))>=ABS(LN(1+G19)),"AOV "&IF(G19>=0,"+","−")&FIXED(ABS(G19)*100,1)&"%","số đơn "&IF(G18>=0,"+","−")&FIXED(ABS(G18)*100,1)&"%")&".","")
B11: =IFERROR("Finance "&IF(C22>=0,"cao","thấp")&" hơn dữ liệu đơn "&FIXED(ABS(C22),0)&" USD; sau khi quy online về ngày giao còn "&FIXED(C23,0)&" USD; "&C24&" cửa hàng vượt ngưỡng (bảng bên dưới, sheet Doi_soat).","")
B12: Chỉ tiêu | C12: Tháng chọn | D12: Tháng trước | E12: so với tháng trước | F12: Cùng kỳ năm trước | G12: so với cùng kỳ | I12: ="Net Revenue "&C5&" bằng "&IFERROR(FIXED(C17/F17*100,0),"–")&"% cùng kỳ năm trước"
B13: Gross Sales (USD) | C13: =SUMIFS(Data_thang!$H$2:$H$2974,Data_thang!$A$2:$A$2974,$D$6,Data_thang!$G$2:$G$2974,$C$6) | D13: =SUMIFS(Data_thang!$H$2:$H$2974,Data_thang!$A$2:$A$2974,$E$6,Data_thang!$G$2:$G$2974,$C$6) | E13: =IFERROR(C13/D13-1,"") | F13: =SUMIFS(Data_thang!$H$2:$H$2974,Data_thang!$A$2:$A$2974,$F$6,Data_thang!$G$2:$G$2974,$C$6) | G13: =IFERROR(C13/F13-1,"") | I13: Net Revenue theo tháng, nghìn USD · 24 tháng đến tháng chọn (điểm xanh)
B14: Giảm giá (USD) | C14: =SUMIFS(Data_thang!$I$2:$I$2974,Data_thang!$A$2:$A$2974,$D$6,Data_thang!$G$2:$G$2974,$C$6) | D14: =SUMIFS(Data_thang!$I$2:$I$2974,Data_thang!$A$2:$A$2974,$E$6,Data_thang!$G$2:$G$2974,$C$6) | E14: =IFERROR(C14/D14-1,"") | F14: =SUMIFS(Data_thang!$I$2:$I$2974,Data_thang!$A$2:$A$2974,$F$6,Data_thang!$G$2:$G$2974,$C$6) | G14: =IFERROR(C14/F14-1,"")
B15: Net Sales (USD) | C15: =SUMIFS(Data_thang!$J$2:$J$2974,Data_thang!$A$2:$A$2974,$D$6,Data_thang!$G$2:$G$2974,$C$6) | D15: =SUMIFS(Data_thang!$J$2:$J$2974,Data_thang!$A$2:$A$2974,$E$6,Data_thang!$G$2:$G$2974,$C$6) | E15: =IFERROR(C15/D15-1,"") | F15: =SUMIFS(Data_thang!$J$2:$J$2974,Data_thang!$A$2:$A$2974,$F$6,Data_thang!$G$2:$G$2974,$C$6) | G15: =IFERROR(C15/F15-1,"")
B16: Hoàn trả (USD) | C16: =SUMIFS(Data_thang!$K$2:$K$2974,Data_thang!$A$2:$A$2974,$D$6,Data_thang!$G$2:$G$2974,$C$6) | D16: =SUMIFS(Data_thang!$K$2:$K$2974,Data_thang!$A$2:$A$2974,$E$6,Data_thang!$G$2:$G$2974,$C$6) | E16: =IFERROR(C16/D16-1,"") | F16: =SUMIFS(Data_thang!$K$2:$K$2974,Data_thang!$A$2:$A$2974,$F$6,Data_thang!$G$2:$G$2974,$C$6) | G16: =IFERROR(C16/F16-1,"")
B17: Net Revenue (USD) | C17: =C15-C16 | D17: =D15-D16 | E17: =IFERROR(C17/D17-1,"") | F17: =F15-F16 | G17: =IFERROR(C17/F17-1,"")
B18: Số đơn hoàn tất | C18: =SUMIFS(Data_thang!$L$2:$L$2974,Data_thang!$A$2:$A$2974,$D$6,Data_thang!$G$2:$G$2974,$C$6) | D18: =SUMIFS(Data_thang!$L$2:$L$2974,Data_thang!$A$2:$A$2974,$E$6,Data_thang!$G$2:$G$2974,$C$6) | E18: =IFERROR(C18/D18-1,"") | F18: =SUMIFS(Data_thang!$L$2:$L$2974,Data_thang!$A$2:$A$2974,$F$6,Data_thang!$G$2:$G$2974,$C$6) | G18: =IFERROR(C18/F18-1,"")
B19: AOV (USD/đơn) | C19: =IFERROR(C15/C18,"") | D19: =IFERROR(D15/D18,"") | E19: =IFERROR(C19/D19-1,"") | F19: =IFERROR(F15/F18,"") | G19: =IFERROR(C19/F19-1,"")
B20: Tỷ lệ hoàn trả | C20: =IFERROR(C16/C15,"") | D20: =IFERROR(D16/D15,"") | E20: =IFERROR(C20-D20,"") | F20: =IFERROR(F16/F15,"") | G20: =IFERROR(C20-F20,"")
B21: Finance Net Revenue (USD) | C21: =SUMIFS(Data_thang!$N$2:$N$2974,Data_thang!$A$2:$A$2974,$D$6,Data_thang!$G$2:$G$2974,$C$6) | D21: =SUMIFS(Data_thang!$N$2:$N$2974,Data_thang!$A$2:$A$2974,$E$6,Data_thang!$G$2:$G$2974,$C$6) | E21: =IFERROR(C21/D21-1,"") | F21: =SUMIFS(Data_thang!$N$2:$N$2974,Data_thang!$A$2:$A$2974,$F$6,Data_thang!$G$2:$G$2974,$C$6) | G21: =IFERROR(C21/F21-1,"")
B22: Δ Finance − dữ liệu đơn (USD) | C22: =C21-C17 | D22: =D21-D17 | F22: =F21-F17
B23: Δ sau khi quy online về ngày giao (USD) | C23: =C21-(SUMIFS(Data_thang!$O$2:$O$2974,Data_thang!$A$2:$A$2974,$D$6,Data_thang!$G$2:$G$2974,$C$6)-C16) | D23: =D21-(SUMIFS(Data_thang!$O$2:$O$2974,Data_thang!$A$2:$A$2974,$E$6,Data_thang!$G$2:$G$2974,$C$6)-D16) | F23: =F21-(SUMIFS(Data_thang!$O$2:$O$2974,Data_thang!$A$2:$A$2974,$F$6,Data_thang!$G$2:$G$2974,$C$6)-F16)
B24: Số cửa hàng vượt ngưỡng | C24: =COUNTIFS(Doi_soat!$A$2:$A$2974,$D$6,Doi_soat!$F$2:$F$2974,$C$6,Doi_soat!$L$2:$L$2974,"⚠ Vượt") | D24: =COUNTIFS(Doi_soat!$A$2:$A$2974,$E$6,Doi_soat!$F$2:$F$2974,$C$6,Doi_soat!$L$2:$L$2974,"⚠ Vượt") | F24: =COUNTIFS(Doi_soat!$A$2:$A$2974,$F$6,Doi_soat!$F$2:$F$2974,$C$6,Doi_soat!$L$2:$L$2974,"⚠ Vượt")
B27: ="Giảm giá và hoàn trả lấy đi "&IFERROR(FIXED((C14+C16)/C13*100,1),"–")&"% Gross Sales" | I27: ="Sau khi quy online về ngày giao, Δ "&C5&" còn "&FIXED(C23,0)&" USD"
B28: Gross Sales | C28: =C13 | I28: Δ sau quy đổi online theo tháng, nghìn USD · tháng chọn tô xanh · chi tiết ở sheet Doi_soat
B29: − Giảm giá | C29: =-C14
B30: − Hoàn trả | C30: =-C16
B31: Net Revenue | C31: =C17
B34: =INDEX(Calc!$N$2:$N$9,1)&" chiếm "&IFERROR(FIXED(INDEX(Calc!$O$2:$O$9,1)*1000/C15*100,0),"–")&"% Net Sales"
B35: Net Sales tháng chọn theo danh mục, nghìn USD
B49: =IF(C24=0,"Không cửa hàng nào vượt ngưỡng tháng "&C5,C24&" cửa hàng vượt ngưỡng tháng "&C5&" — cần giải thích nguyên nhân và số tiền")
B50: Cửa hàng | C50: Quốc gia | D50: Mã CH | E50: Net Revenue đơn | F50: Finance | G50: Δ (USD) | H50: Δ % | I50: Δ sau quy đổi
B51: =IF(LARGE(Doi_soat!$M$2:$M$2974,1)=0,"",INDEX(Doi_soat!$D$2:$D$2974,MATCH(LARGE(Doi_soat!$M$2:$M$2974,1),Doi_soat!$M$2:$M$2974,0))) | C51: =IF(LARGE(Doi_soat!$M$2:$M$2974,1)=0,"",INDEX(Doi_soat!$E$2:$E$2974,MATCH(LARGE(Doi_soat!$M$2:$M$2974,1),Doi_soat!$M$2:$M$2974,0))) | D51: =IF(LARGE(Doi_soat!$M$2:$M$2974,1)=0,"",INDEX(Doi_soat!$C$2:$C$2974,MATCH(LARGE(Doi_soat!$M$2:$M$2974,1),Doi_soat!$M$2:$M$2974,0))) | E51: =IF(LARGE(Doi_soat!$M$2:$M$2974,1)=0,"",INDEX(Doi_soat!$G$2:$G$2974,MATCH(LARGE(Doi_soat!$M$2:$M$2974,1),Doi_soat!$M$2:$M$2974,0))) | F51: =IF(LARGE(Doi_soat!$M$2:$M$2974,1)=0,"",INDEX(Doi_soat!$H$2:$H$2974,MATCH(LARGE(Doi_soat!$M$2:$M$2974,1),Doi_soat!$M$2:$M$2974,0))) | G51: =IF(LARGE(Doi_soat!$M$2:$M$2974,1)=0,"",INDEX(Doi_soat!$I$2:$I$2974,MATCH(LARGE(Doi_soat!$M$2:$M$2974,1),Doi_soat!$M$2:$M$2974,0))) | H51: =IF(LARGE(Doi_soat!$M$2:$M$2974,1)=0,"",INDEX(Doi_soat!$J$2:$J$2974,MATCH(LARGE(Doi_soat!$M$2:$M$2974,1),Doi_soat!$M$2:$M$2974,0))) | I51: =IF(LARGE(Doi_soat!$M$2:$M$2974,1)=0,"",INDEX(Doi_soat!$K$2:$K$2974,MATCH(LARGE(Doi_soat!$M$2:$M$2974,1),Doi_soat!$M$2:$M$2974,0)))
B52: =IF(LARGE(Doi_soat!$M$2:$M$2974,2)=0,"",INDEX(Doi_soat!$D$2:$D$2974,MATCH(LARGE(Doi_soat!$M$2:$M$2974,2),Doi_soat!$M$2:$M$2974,0))) | C52: =IF(LARGE(Doi_soat!$M$2:$M$2974,2)=0,"",INDEX(Doi_soat!$E$2:$E$2974,MATCH(LARGE(Doi_soat!$M$2:$M$2974,2),Doi_soat!$M$2:$M$2974,0))) | D52: =IF(LARGE(Doi_soat!$M$2:$M$2974,2)=0,"",INDEX(Doi_soat!$C$2:$C$2974,MATCH(LARGE(Doi_soat!$M$2:$M$2974,2),Doi_soat!$M$2:$M$2974,0))) | E52: =IF(LARGE(Doi_soat!$M$2:$M$2974,2)=0,"",INDEX(Doi_soat!$G$2:$G$2974,MATCH(LARGE(Doi_soat!$M$2:$M$2974,2),Doi_soat!$M$2:$M$2974,0))) | F52: =IF(LARGE(Doi_soat!$M$2:$M$2974,2)=0,"",INDEX(Doi_soat!$H$2:$H$2974,MATCH(LARGE(Doi_soat!$M$2:$M$2974,2),Doi_soat!$M$2:$M$2974,0))) | G52: =IF(LARGE(Doi_soat!$M$2:$M$2974,2)=0,"",INDEX(Doi_soat!$I$2:$I$2974,MATCH(LARGE(Doi_soat!$M$2:$M$2974,2),Doi_soat!$M$2:$M$2974,0))) | H52: =IF(LARGE(Doi_soat!$M$2:$M$2974,2)=0,"",INDEX(Doi_soat!$J$2:$J$2974,MATCH(LARGE(Doi_soat!$M$2:$M$2974,2),Doi_soat!$M$2:$M$2974,0))) | I52: =IF(LARGE(Doi_soat!$M$2:$M$2974,2)=0,"",INDEX(Doi_soat!$K$2:$K$2974,MATCH(LARGE(Doi_soat!$M$2:$M$2974,2),Doi_soat!$M$2:$M$2974,0)))
B53: =IF(LARGE(Doi_soat!$M$2:$M$2974,3)=0,"",INDEX(Doi_soat!$D$2:$D$2974,MATCH(LARGE(Doi_soat!$M$2:$M$2974,3),Doi_soat!$M$2:$M$2974,0))) | C53: =IF(LARGE(Doi_soat!$M$2:$M$2974,3)=0,"",INDEX(Doi_soat!$E$2:$E$2974,MATCH(LARGE(Doi_soat!$M$2:$M$2974,3),Doi_soat!$M$2:$M$2974,0))) | D53: =IF(LARGE(Doi_soat!$M$2:$M$2974,3)=0,"",INDEX(Doi_soat!$C$2:$C$2974,MATCH(LARGE(Doi_soat!$M$2:$M$2974,3),Doi_soat!$M$2:$M$2974,0))) | E53: =IF(LARGE(Doi_soat!$M$2:$M$2974,3)=0,"",INDEX(Doi_soat!$G$2:$G$2974,MATCH(LARGE(Doi_soat!$M$2:$M$2974,3),Doi_soat!$M$2:$M$2974,0))) | F53: =IF(LARGE(Doi_soat!$M$2:$M$2974,3)=0,"",INDEX(Doi_soat!$H$2:$H$2974,MATCH(LARGE(Doi_soat!$M$2:$M$2974,3),Doi_soat!$M$2:$M$2974,0))) | G53: =IF(LARGE(Doi_soat!$M$2:$M$2974,3)=0,"",INDEX(Doi_soat!$I$2:$I$2974,MATCH(LARGE(Doi_soat!$M$2:$M$2974,3),Doi_soat!$M$2:$M$2974,0))) | H53: =IF(LARGE(Doi_soat!$M$2:$M$2974,3)=0,"",INDEX(Doi_soat!$J$2:$J$2974,MATCH(LARGE(Doi_soat!$M$2:$M$2974,3),Doi_soat!$M$2:$M$2974,0))) | I53: =IF(LARGE(Doi_soat!$M$2:$M$2974,3)=0,"",INDEX(Doi_soat!$K$2:$K$2974,MATCH(LARGE(Doi_soat!$M$2:$M$2974,3),Doi_soat!$M$2:$M$2974,0)))
B54: =IF(LARGE(Doi_soat!$M$2:$M$2974,4)=0,"",INDEX(Doi_soat!$D$2:$D$2974,MATCH(LARGE(Doi_soat!$M$2:$M$2974,4),Doi_soat!$M$2:$M$2974,0))) | C54: =IF(LARGE(Doi_soat!$M$2:$M$2974,4)=0,"",INDEX(Doi_soat!$E$2:$E$2974,MATCH(LARGE(Doi_soat!$M$2:$M$2974,4),Doi_soat!$M$2:$M$2974,0))) | D54: =IF(LARGE(Doi_soat!$M$2:$M$2974,4)=0,"",INDEX(Doi_soat!$C$2:$C$2974,MATCH(LARGE(Doi_soat!$M$2:$M$2974,4),Doi_soat!$M$2:$M$2974,0))) | E54: =IF(LARGE(Doi_soat!$M$2:$M$2974,4)=0,"",INDEX(Doi_soat!$G$2:$G$2974,MATCH(LARGE(Doi_soat!$M$2:$M$2974,4),Doi_soat!$M$2:$M$2974,0))) | F54: =IF(LARGE(Doi_soat!$M$2:$M$2974,4)=0,"",INDEX(Doi_soat!$H$2:$H$2974,MATCH(LARGE(Doi_soat!$M$2:$M$2974,4),Doi_soat!$M$2:$M$2974,0))) | G54: =IF(LARGE(Doi_soat!$M$2:$M$2974,4)=0,"",INDEX(Doi_soat!$I$2:$I$2974,MATCH(LARGE(Doi_soat!$M$2:$M$2974,4),Doi_soat!$M$2:$M$2974,0))) | H54: =IF(LARGE(Doi_soat!$M$2:$M$2974,4)=0,"",INDEX(Doi_soat!$J$2:$J$2974,MATCH(LARGE(Doi_soat!$M$2:$M$2974,4),Doi_soat!$M$2:$M$2974,0))) | I54: =IF(LARGE(Doi_soat!$M$2:$M$2974,4)=0,"",INDEX(Doi_soat!$K$2:$K$2974,MATCH(LARGE(Doi_soat!$M$2:$M$2974,4),Doi_soat!$M$2:$M$2974,0)))
B55: =IF(LARGE(Doi_soat!$M$2:$M$2974,5)=0,"",INDEX(Doi_soat!$D$2:$D$2974,MATCH(LARGE(Doi_soat!$M$2:$M$2974,5),Doi_soat!$M$2:$M$2974,0))) | C55: =IF(LARGE(Doi_soat!$M$2:$M$2974,5)=0,"",INDEX(Doi_soat!$E$2:$E$2974,MATCH(LARGE(Doi_soat!$M$2:$M$2974,5),Doi_soat!$M$2:$M$2974,0))) | D55: =IF(LARGE(Doi_soat!$M$2:$M$2974,5)=0,"",INDEX(Doi_soat!$C$2:$C$2974,MATCH(LARGE(Doi_soat!$M$2:$M$2974,5),Doi_soat!$M$2:$M$2974,0))) | E55: =IF(LARGE(Doi_soat!$M$2:$M$2974,5)=0,"",INDEX(Doi_soat!$G$2:$G$2974,MATCH(LARGE(Doi_soat!$M$2:$M$2974,5),Doi_soat!$M$2:$M$2974,0))) | F55: =IF(LARGE(Doi_soat!$M$2:$M$2974,5)=0,"",INDEX(Doi_soat!$H$2:$H$2974,MATCH(LARGE(Doi_soat!$M$2:$M$2974,5),Doi_soat!$M$2:$M$2974,0))) | G55: =IF(LARGE(Doi_soat!$M$2:$M$2974,5)=0,"",INDEX(Doi_soat!$I$2:$I$2974,MATCH(LARGE(Doi_soat!$M$2:$M$2974,5),Doi_soat!$M$2:$M$2974,0))) | H55: =IF(LARGE(Doi_soat!$M$2:$M$2974,5)=0,"",INDEX(Doi_soat!$J$2:$J$2974,MATCH(LARGE(Doi_soat!$M$2:$M$2974,5),Doi_soat!$M$2:$M$2974,0))) | I55: =IF(LARGE(Doi_soat!$M$2:$M$2974,5)=0,"",INDEX(Doi_soat!$K$2:$K$2974,MATCH(LARGE(Doi_soat!$M$2:$M$2974,5),Doi_soat!$M$2:$M$2974,0)))
B56: =IF(LARGE(Doi_soat!$M$2:$M$2974,6)=0,"",INDEX(Doi_soat!$D$2:$D$2974,MATCH(LARGE(Doi_soat!$M$2:$M$2974,6),Doi_soat!$M$2:$M$2974,0))) | C56: =IF(LARGE(Doi_soat!$M$2:$M$2974,6)=0,"",INDEX(Doi_soat!$E$2:$E$2974,MATCH(LARGE(Doi_soat!$M$2:$M$2974,6),Doi_soat!$M$2:$M$2974,0))) | D56: =IF(LARGE(Doi_soat!$M$2:$M$2974,6)=0,"",INDEX(Doi_soat!$C$2:$C$2974,MATCH(LARGE(Doi_soat!$M$2:$M$2974,6),Doi_soat!$M$2:$M$2974,0))) | E56: =IF(LARGE(Doi_soat!$M$2:$M$2974,6)=0,"",INDEX(Doi_soat!$G$2:$G$2974,MATCH(LARGE(Doi_soat!$M$2:$M$2974,6),Doi_soat!$M$2:$M$2974,0))) | F56: =IF(LARGE(Doi_soat!$M$2:$M$2974,6)=0,"",INDEX(Doi_soat!$H$2:$H$2974,MATCH(LARGE(Doi_soat!$M$2:$M$2974,6),Doi_soat!$M$2:$M$2974,0))) | G56: =IF(LARGE(Doi_soat!$M$2:$M$2974,6)=0,"",INDEX(Doi_soat!$I$2:$I$2974,MATCH(LARGE(Doi_soat!$M$2:$M$2974,6),Doi_soat!$M$2:$M$2974,0))) | H56: =IF(LARGE(Doi_soat!$M$2:$M$2974,6)=0,"",INDEX(Doi_soat!$J$2:$J$2974,MATCH(LARGE(Doi_soat!$M$2:$M$2974,6),Doi_soat!$M$2:$M$2974,0))) | I56: =IF(LARGE(Doi_soat!$M$2:$M$2974,6)=0,"",INDEX(Doi_soat!$K$2:$K$2974,MATCH(LARGE(Doi_soat!$M$2:$M$2974,6),Doi_soat!$M$2:$M$2974,0)))
B57: =IF(LARGE(Doi_soat!$M$2:$M$2974,7)=0,"",INDEX(Doi_soat!$D$2:$D$2974,MATCH(LARGE(Doi_soat!$M$2:$M$2974,7),Doi_soat!$M$2:$M$2974,0))) | C57: =IF(LARGE(Doi_soat!$M$2:$M$2974,7)=0,"",INDEX(Doi_soat!$E$2:$E$2974,MATCH(LARGE(Doi_soat!$M$2:$M$2974,7),Doi_soat!$M$2:$M$2974,0))) | D57: =IF(LARGE(Doi_soat!$M$2:$M$2974,7)=0,"",INDEX(Doi_soat!$C$2:$C$2974,MATCH(LARGE(Doi_soat!$M$2:$M$2974,7),Doi_soat!$M$2:$M$2974,0))) | E57: =IF(LARGE(Doi_soat!$M$2:$M$2974,7)=0,"",INDEX(Doi_soat!$G$2:$G$2974,MATCH(LARGE(Doi_soat!$M$2:$M$2974,7),Doi_soat!$M$2:$M$2974,0))) | F57: =IF(LARGE(Doi_soat!$M$2:$M$2974,7)=0,"",INDEX(Doi_soat!$H$2:$H$2974,MATCH(LARGE(Doi_soat!$M$2:$M$2974,7),Doi_soat!$M$2:$M$2974,0))) | G57: =IF(LARGE(Doi_soat!$M$2:$M$2974,7)=0,"",INDEX(Doi_soat!$I$2:$I$2974,MATCH(LARGE(Doi_soat!$M$2:$M$2974,7),Doi_soat!$M$2:$M$2974,0))) | H57: =IF(LARGE(Doi_soat!$M$2:$M$2974,7)=0,"",INDEX(Doi_soat!$J$2:$J$2974,MATCH(LARGE(Doi_soat!$M$2:$M$2974,7),Doi_soat!$M$2:$M$2974,0))) | I57: =IF(LARGE(Doi_soat!$M$2:$M$2974,7)=0,"",INDEX(Doi_soat!$K$2:$K$2974,MATCH(LARGE(Doi_soat!$M$2:$M$2974,7),Doi_soat!$M$2:$M$2974,0)))
B58: =IF(LARGE(Doi_soat!$M$2:$M$2974,8)=0,"",INDEX(Doi_soat!$D$2:$D$2974,MATCH(LARGE(Doi_soat!$M$2:$M$2974,8),Doi_soat!$M$2:$M$2974,0))) | C58: =IF(LARGE(Doi_soat!$M$2:$M$2974,8)=0,"",INDEX(Doi_soat!$E$2:$E$2974,MATCH(LARGE(Doi_soat!$M$2:$M$2974,8),Doi_soat!$M$2:$M$2974,0))) | D58: =IF(LARGE(Doi_soat!$M$2:$M$2974,8)=0,"",INDEX(Doi_soat!$C$2:$C$2974,MATCH(LARGE(Doi_soat!$M$2:$M$2974,8),Doi_soat!$M$2:$M$2974,0))) | E58: =IF(LARGE(Doi_soat!$M$2:$M$2974,8)=0,"",INDEX(Doi_soat!$G$2:$G$2974,MATCH(LARGE(Doi_soat!$M$2:$M$2974,8),Doi_soat!$M$2:$M$2974,0))) | F58: =IF(LARGE(Doi_soat!$M$2:$M$2974,8)=0,"",INDEX(Doi_soat!$H$2:$H$2974,MATCH(LARGE(Doi_soat!$M$2:$M$2974,8),Doi_soat!$M$2:$M$2974,0))) | G58: =IF(LARGE(Doi_soat!$M$2:$M$2974,8)=0,"",INDEX(Doi_soat!$I$2:$I$2974,MATCH(LARGE(Doi_soat!$M$2:$M$2974,8),Doi_soat!$M$2:$M$2974,0))) | H58: =IF(LARGE(Doi_soat!$M$2:$M$2974,8)=0,"",INDEX(Doi_soat!$J$2:$J$2974,MATCH(LARGE(Doi_soat!$M$2:$M$2974,8),Doi_soat!$M$2:$M$2974,0))) | I58: =IF(LARGE(Doi_soat!$M$2:$M$2974,8)=0,"",INDEX(Doi_soat!$K$2:$K$2974,MATCH(LARGE(Doi_soat!$M$2:$M$2974,8),Doi_soat!$M$2:$M$2974,0)))
B59: =IF(LARGE(Doi_soat!$M$2:$M$2974,9)=0,"",INDEX(Doi_soat!$D$2:$D$2974,MATCH(LARGE(Doi_soat!$M$2:$M$2974,9),Doi_soat!$M$2:$M$2974,0))) | C59: =IF(LARGE(Doi_soat!$M$2:$M$2974,9)=0,"",INDEX(Doi_soat!$E$2:$E$2974,MATCH(LARGE(Doi_soat!$M$2:$M$2974,9),Doi_soat!$M$2:$M$2974,0))) | D59: =IF(LARGE(Doi_soat!$M$2:$M$2974,9)=0,"",INDEX(Doi_soat!$C$2:$C$2974,MATCH(LARGE(Doi_soat!$M$2:$M$2974,9),Doi_soat!$M$2:$M$2974,0))) | E59: =IF(LARGE(Doi_soat!$M$2:$M$2974,9)=0,"",INDEX(Doi_soat!$G$2:$G$2974,MATCH(LARGE(Doi_soat!$M$2:$M$2974,9),Doi_soat!$M$2:$M$2974,0))) | F59: =IF(LARGE(Doi_soat!$M$2:$M$2974,9)=0,"",INDEX(Doi_soat!$H$2:$H$2974,MATCH(LARGE(Doi_soat!$M$2:$M$2974,9),Doi_soat!$M$2:$M$2974,0))) | G59: =IF(LARGE(Doi_soat!$M$2:$M$2974,9)=0,"",INDEX(Doi_soat!$I$2:$I$2974,MATCH(LARGE(Doi_soat!$M$2:$M$2974,9),Doi_soat!$M$2:$M$2974,0))) | H59: =IF(LARGE(Doi_soat!$M$2:$M$2974,9)=0,"",INDEX(Doi_soat!$J$2:$J$2974,MATCH(LARGE(Doi_soat!$M$2:$M$2974,9),Doi_soat!$M$2:$M$2974,0))) | I59: =IF(LARGE(Doi_soat!$M$2:$M$2974,9)=0,"",INDEX(Doi_soat!$K$2:$K$2974,MATCH(LARGE(Doi_soat!$M$2:$M$2974,9),Doi_soat!$M$2:$M$2974,0)))
B60: =IF(LARGE(Doi_soat!$M$2:$M$2974,10)=0,"",INDEX(Doi_soat!$D$2:$D$2974,MATCH(LARGE(Doi_soat!$M$2:$M$2974,10),Doi_soat!$M$2:$M$2974,0))) | C60: =IF(LARGE(Doi_soat!$M$2:$M$2974,10)=0,"",INDEX(Doi_soat!$E$2:$E$2974,MATCH(LARGE(Doi_soat!$M$2:$M$2974,10),Doi_soat!$M$2:$M$2974,0))) | D60: =IF(LARGE(Doi_soat!$M$2:$M$2974,10)=0,"",INDEX(Doi_soat!$C$2:$C$2974,MATCH(LARGE(Doi_soat!$M$2:$M$2974,10),Doi_soat!$M$2:$M$2974,0))) | E60: =IF(LARGE(Doi_soat!$M$2:$M$2974,10)=0,"",INDEX(Doi_soat!$G$2:$G$2974,MATCH(LARGE(Doi_soat!$M$2:$M$2974,10),Doi_soat!$M$2:$M$2974,0))) | F60: =IF(LARGE(Doi_soat!$M$2:$M$2974,10)=0,"",INDEX(Doi_soat!$H$2:$H$2974,MATCH(LARGE(Doi_soat!$M$2:$M$2974,10),Doi_soat!$M$2:$M$2974,0))) | G60: =IF(LARGE(Doi_soat!$M$2:$M$2974,10)=0,"",INDEX(Doi_soat!$I$2:$I$2974,MATCH(LARGE(Doi_soat!$M$2:$M$2974,10),Doi_soat!$M$2:$M$2974,0))) | H60: =IF(LARGE(Doi_soat!$M$2:$M$2974,10)=0,"",INDEX(Doi_soat!$J$2:$J$2974,MATCH(LARGE(Doi_soat!$M$2:$M$2974,10),Doi_soat!$M$2:$M$2974,0))) | I60: =IF(LARGE(Doi_soat!$M$2:$M$2974,10)=0,"",INDEX(Doi_soat!$K$2:$K$2974,MATCH(LARGE(Doi_soat!$M$2:$M$2974,10),Doi_soat!$M$2:$M$2974,0)))

Sheet Doi_soat
A1: month_id | B1: Tháng | C1: Mã CH | D1: Cửa hàng | E1: Quốc gia | F1: Kênh | G1: Net Revenue đơn (USD) | H1: Finance (USD) | I1: Δ (USD) | J1: Δ % | K1: Δ sau quy đổi online (USD) | L1: Cờ | M1: khoá xếp (Dashboard)
A2: =Data_thang!A2 | B2: =Data_thang!B2 | C2: =Data_thang!D2 | D2: =Data_thang!E2 | E2: =Data_thang!F2 | F2: =Data_thang!G2 | G2: =Data_thang!J2-Data_thang!K2 | H2: =Data_thang!N2 | I2: =H2-G2 | J2: =IF(H2=0,IF(I2=0,0,1),I2/ABS(H2)) | K2: =H2-(Data_thang!O2-Data_thang!K2) | L2: =IF(AND(ABS(I2)>Dashboard!$G$6,ABS(J2)>Dashboard!$H$6),"⚠ Vượt","") | M2: =IF(AND(A2=Dashboard!$D$6,OR(Dashboard!$C$6="*",F2=Dashboard!$C$6),L2<>""),ABS(I2)+ROW()/1000000000,0)
A3: =Data_thang!A3 | B3: =Data_thang!B3 | C3: =Data_thang!D3 | D3: =Data_thang!E3 | E3: =Data_thang!F3 | F3: =Data_thang!G3 | G3: =Data_thang!J3-Data_thang!K3 | H3: =Data_thang!N3 | I3: =H3-G3 | J3: =IF(H3=0,IF(I3=0,0,1),I3/ABS(H3)) | K3: =H3-(Data_thang!O3-Data_thang!K3) | L3: =IF(AND(ABS(I3)>Dashboard!$G$6,ABS(J3)>Dashboard!$H$6),"⚠ Vượt","") | M3: =IF(AND(A3=Dashboard!$D$6,OR(Dashboard!$C$6="*",F3=Dashboard!$C$6),L3<>""),ABS(I3)+ROW()/1000000000,0)
A4: =Data_thang!A4 | B4: =Data_thang!B4 | C4: =Data_thang!D4 | D4: =Data_thang!E4 | E4: =Data_thang!F4 | F4: =Data_thang!G4 | G4: =Data_thang!J4-Data_thang!K4 | H4: =Data_thang!N4 | I4: =H4-G4 | J4: =IF(H4=0,IF(I4=0,0,1),I4/ABS(H4)) | K4: =H4-(Data_thang!O4-Data_thang!K4) | L4: =IF(AND(ABS(I4)>Dashboard!$G$6,ABS(J4)>Dashboard!$H$6),"⚠ Vượt","") | M4: =IF(AND(A4=Dashboard!$D$6,OR(Dashboard!$C$6="*",F4=Dashboard!$C$6),L4<>""),ABS(I4)+ROW()/1000000000,0)
A5: =Data_thang!A5 | B5: =Data_thang!B5 | C5: =Data_thang!D5 | D5: =Data_thang!E5 | E5: =Data_thang!F5 | F5: =Data_thang!G5 | G5: =Data_thang!J5-Data_thang!K5 | H5: =Data_thang!N5 | I5: =H5-G5 | J5: =IF(H5=0,IF(I5=0,0,1),I5/ABS(H5)) | K5: =H5-(Data_thang!O5-Data_thang!K5) | L5: =IF(AND(ABS(I5)>Dashboard!$G$6,ABS(J5)>Dashboard!$H$6),"⚠ Vượt","") | M5: =IF(AND(A5=Dashboard!$D$6,OR(Dashboard!$C$6="*",F5=Dashboard!$C$6),L5<>""),ABS(I5)+ROW()/1000000000,0)
A6: =Data_thang!A6 | B6: =Data_thang!B6 | C6: =Data_thang!D6 | D6: =Data_thang!E6 | E6: =Data_thang!F6 | F6: =Data_thang!G6 | G6: =Data_thang!J6-Data_thang!K6 | H6: =Data_thang!N6 | I6: =H6-G6 | J6: =IF(H6=0,IF(I6=0,0,1),I6/ABS(H6)) | K6: =H6-(Data_thang!O6-Data_thang!K6) | L6: =IF(AND(ABS(I6)>Dashboard!$G$6,ABS(J6)>Dashboard!$H$6),"⚠ Vượt","") | M6: =IF(AND(A6=Dashboard!$D$6,OR(Dashboard!$C$6="*",F6=Dashboard!$C$6),L6<>""),ABS(I6)+ROW()/1000000000,0)
A7: =Data_thang!A7 | B7: =Data_thang!B7 | C7: =Data_thang!D7 | D7: =Data_thang!E7 | E7: =Data_thang!F7 | F7: =Data_thang!G7 | G7: =Data_thang!J7-Data_thang!K7 | H7: =Data_thang!N7 | I7: =H7-G7 | J7: =IF(H7=0,IF(I7=0,0,1),I7/ABS(H7)) | K7: =H7-(Data_thang!O7-Data_thang!K7) | L7: =IF(AND(ABS(I7)>Dashboard!$G$6,ABS(J7)>Dashboard!$H$6),"⚠ Vượt","") | M7: =IF(AND(A7=Dashboard!$D$6,OR(Dashboard!$C$6="*",F7=Dashboard!$C$6),L7<>""),ABS(I7)+ROW()/1000000000,0)
A8: =Data_thang!A8 | B8: =Data_thang!B8 | C8: =Data_thang!D8 | D8: =Data_thang!E8 | E8: =Data_thang!F8 | F8: =Data_thang!G8 | G8: =Data_thang!J8-Data_thang!K8 | H8: =Data_thang!N8 | I8: =H8-G8 | J8: =IF(H8=0,IF(I8=0,0,1),I8/ABS(H8)) | K8: =H8-(Data_thang!O8-Data_thang!K8) | L8: =IF(AND(ABS(I8)>Dashboard!$G$6,ABS(J8)>Dashboard!$H$6),"⚠ Vượt","") | M8: =IF(AND(A8=Dashboard!$D$6,OR(Dashboard!$C$6="*",F8=Dashboard!$C$6),L8<>""),ABS(I8)+ROW()/1000000000,0)
A9: =Data_thang!A9 | B9: =Data_thang!B9 | C9: =Data_thang!D9 | D9: =Data_thang!E9 | E9: =Data_thang!F9 | F9: =Data_thang!G9 | G9: =Data_thang!J9-Data_thang!K9 | H9: =Data_thang!N9 | I9: =H9-G9 | J9: =IF(H9=0,IF(I9=0,0,1),I9/ABS(H9)) | K9: =H9-(Data_thang!O9-Data_thang!K9) | L9: =IF(AND(ABS(I9)>Dashboard!$G$6,ABS(J9)>Dashboard!$H$6),"⚠ Vượt","") | M9: =IF(AND(A9=Dashboard!$D$6,OR(Dashboard!$C$6="*",F9=Dashboard!$C$6),L9<>""),ABS(I9)+ROW()/1000000000,0)
A10: =Data_thang!A10 | B10: =Data_thang!B10 | C10: =Data_thang!D10 | D10: =Data_thang!E10 | E10: =Data_thang!F10 | F10: =Data_thang!G10 | G10: =Data_thang!J10-Data_thang!K10 | H10: =Data_thang!N10 | I10: =H10-G10 | J10: =IF(H10=0,IF(I10=0,0,1),I10/ABS(H10)) | K10: =H10-(Data_thang!O10-Data_thang!K10) | L10: =IF(AND(ABS(I10)>Dashboard!$G$6,ABS(J10)>Dashboard!$H$6),"⚠ Vượt","") | M10: =IF(AND(A10=Dashboard!$D$6,OR(Dashboard!$C$6="*",F10=Dashboard!$C$6),L10<>""),ABS(I10)+ROW()/1000000000,0)
A11: =Data_thang!A11 | B11: =Data_thang!B11 | C11: =Data_thang!D11 | D11: =Data_thang!E11 | E11: =Data_thang!F11 | F11: =Data_thang!G11 | G11: =Data_thang!J11-Data_thang!K11 | H11: =Data_thang!N11 | I11: =H11-G11 | J11: =IF(H11=0,IF(I11=0,0,1),I11/ABS(H11)) | K11: =H11-(Data_thang!O11-Data_thang!K11) | L11: =IF(AND(ABS(I11)>Dashboard!$G$6,ABS(J11)>Dashboard!$H$6),"⚠ Vượt","") | M11: =IF(AND(A11=Dashboard!$D$6,OR(Dashboard!$C$6="*",F11=Dashboard!$C$6),L11<>""),ABS(I11)+ROW()/1000000000,0)
A12: =Data_thang!A12 | B12: =Data_thang!B12 | C12: =Data_thang!D12 | D12: =Data_thang!E12 | E12: =Data_thang!F12 | F12: =Data_thang!G12 | G12: =Data_thang!J12-Data_thang!K12 | H12: =Data_thang!N12 | I12: =H12-G12 | J12: =IF(H12=0,IF(I12=0,0,1),I12/ABS(H12)) | K12: =H12-(Data_thang!O12-Data_thang!K12) | L12: =IF(AND(ABS(I12)>Dashboard!$G$6,ABS(J12)>Dashboard!$H$6),"⚠ Vượt","") | M12: =IF(AND(A12=Dashboard!$D$6,OR(Dashboard!$C$6="*",F12=Dashboard!$C$6),L12<>""),ABS(I12)+ROW()/1000000000,0)
A13: =Data_thang!A13 | B13: =Data_thang!B13 | C13: =Data_thang!D13 | D13: =Data_thang!E13 | E13: =Data_thang!F13 | F13: =Data_thang!G13 | G13: =Data_thang!J13-Data_thang!K13 | H13: =Data_thang!N13 | I13: =H13-G13 | J13: =IF(H13=0,IF(I13=0,0,1),I13/ABS(H13)) | K13: =H13-(Data_thang!O13-Data_thang!K13) | L13: =IF(AND(ABS(I13)>Dashboard!$G$6,ABS(J13)>Dashboard!$H$6),"⚠ Vượt","") | M13: =IF(AND(A13=Dashboard!$D$6,OR(Dashboard!$C$6="*",F13=Dashboard!$C$6),L13<>""),ABS(I13)+ROW()/1000000000,0)
... A2974: =Data_thang!A2974 | B2974: =Data_thang!B2974 | C2974: =Data_thang!D2974 | D2974: =Data_thang!E2974 | E2974: =Data_thang!F2974 | F2974: =Data_thang!G2974 | G2974: =Data_thang!J2974-Data_thang!K2974 | H2974: =Data_thang!N2974 | I2974: =H2974-G2974 | J2974: =IF(H2974=0,IF(I2974=0,0,1),I2974/ABS(H2974)) | K2974: =H2974-(Data_thang!O2974-Data_thang!K2974) | L2974: =IF(AND(ABS(I2974)>Dashboard!$G$6,ABS(J2974)>Dashboard!$H$6),"⚠ Vượt","") | M2974: =IF(AND(A2974=Dashboard!$D$6,OR(Dashboard!$C$6="*",F2974=Dashboard!$C$6),L2974<>""),ABS(I2974)+ROW()/1000000000,0)

Sheet Data_thang
A1: month_id | B1: month_label | C1: store_key | D1: store_code | E1: store_name | F1: country | G1: channel | H1: gross_sales | I1: discounts | J1: net_sales | K1: returns | L1: orders | M1: units | N1: finance_net_revenue | O1: net_sales_delivery_basis | P1: cancelled_orders | Q1: pending_orders | R1: duplicate_lines
A2: 201601 | B2: 01/2016 | C2: 0 | D2: ONL | E2: Nexa Online (website/app) | F2: Online | G2: ONLINE | H2: 68194.13 | I2: 2744.77 | J2: 65449.36 | K2: 538.65 | L2: 43 | M2: 299 | N2: 53383.77 | O2: 53922.42 | P2: 0 | Q2: 0 | R2: 0
A3: 201601 | B3: 01/2016 | C3: 2 | D3: S02 | E3: Nexa Northern Territory (S02) | F3: Úc | G3: POS | H3: 3846.85 | I3: 93.84 | J3: 3753.01 | K3: 0 | L3: 2 | M3: 18 | N3: 3753.01 | O3: 3753.01 | P3: 0 | Q3: 0 | R3: 0
A4: 201601 | B4: 01/2016 | C4: 4 | D4: S04 | E4: Nexa Tasmania (S04) | F4: Úc | G4: POS | H4: 1914.9 | I4: 95.75 | J4: 1819.15 | K4: 0 | L4: 2 | M4: 3 | N4: 1819.15 | O4: 1819.15 | P4: 0 | Q4: 0 | R4: 0
A5: 201601 | B5: 01/2016 | C5: 5 | D5: S05 | E5: Nexa Victoria (S05) | F5: Úc | G5: POS | H5: 20142.69 | I5: 0 | J5: 20142.69 | K5: 0 | L5: 4 | M5: 54 | N5: 20142.69 | O5: 20142.69 | P5: 0 | Q5: 0 | R5: 0
A6: 201601 | B6: 01/2016 | C6: 6 | D6: S06 | E6: Nexa Western Australia (S06) | F6: Úc | G6: POS | H6: 11067.21 | I6: 2.16 | J6: 11065.05 | K6: 219.95 | L6: 6 | M6: 35 | N6: 10845.1 | O6: 11065.05 | P6: 0 | Q6: 0 | R6: 0
A7: 201601 | B7: 01/2016 | C7: 8 | D7: S08 | E7: Nexa Newfoundland and Labrador (S08) | F7: Canada | G7: POS | H7: 25219.43 | I7: 310.78 | J7: 24908.65 | K7: 0 | L7: 12 | M7: 93 | N7: 24908.65 | O7: 24908.65 | P7: 0 | Q7: 0 | R7: 0
A8: 201601 | B8: 01/2016 | C8: 9 | D8: S09 | E8: Nexa Northwest Territories (S09) | F8: Canada | G8: POS | H8: 19769.88 | I8: 840.59 | J8: 18929.29 | K8: 104.49 | L8: 4 | M8: 51 | N8: 18824.8 | O8: 18929.29 | P8: 0 | Q8: 0 | R8: 0
A9: 201601 | B9: 01/2016 | C9: 10 | D9: S10 | E9: Nexa Nunavut (S10) | F9: Canada | G9: POS | H9: 6571.03 | I9: 3.4 | J9: 6567.63 | K9: 0 | L9: 6 | M9: 43 | N9: 6567.63 | O9: 6567.63 | P9: 0 | Q9: 0 | R9: 0
A10: 201601 | B10: 01/2016 | C10: 12 | D10: S12 | E10: Nexa Basse-Normandie (S12) | F10: Pháp | G10: POS | H10: 5515.2 | I10: 275.76 | J10: 5239.44 | K10: 0 | L10: 1 | M10: 24 | N10: 5239.44 | O10: 5239.44 | P10: 0 | Q10: 0 | R10: 1
A11: 201601 | B11: 01/2016 | C11: 15 | D11: S15 | E11: Nexa La Réunion (S15) | F11: Pháp | G11: POS | H11: 1332.8 | I11: 66.64 | J11: 1266.16 | K11: 0 | L11: 1 | M11: 8 | N11: 1266.16 | O11: 1266.16 | P11: 0 | Q11: 0 | R11: 0
A12: 201601 | B12: 01/2016 | C12: 16 | D12: S16 | E12: Nexa Limousin (S16) | F12: Pháp | G12: POS | H12: 1954.6 | I12: 2.08 | J12: 1952.52 | K12: 0 | L12: 3 | M12: 12 | N12: 1952.52 | O12: 1952.52 | P12: 0 | Q12: 0 | R12: 0
A13: 201601 | B13: 01/2016 | C13: 17 | D13: S17 | E13: Nexa Martinique (S17) | F13: Pháp | G13: POS | H13: 2201.15 | I13: 25.35 | J13: 2175.8 | K13: 0 | L13: 2 | M13: 13 | N13: 2175.8 | O13: 2175.8 | P13: 0 | Q13: 0 | R13: 0
... A2974: 202102 | B2974: 02/2021 | C2974: 66 | D2974: S66 | E2974: Nexa Wyoming (S66) | F2974: Mỹ | G2974: POS | H2974: 7747.56 | I2974: 0 | J2974: 7747.56 | K2974: 115.99 | L2974: 6 | M2974: 53 | N2974: 7631.57 | O2974: 7747.56 | P2974: 0 | Q2974: 0 | R2974: 0

Sheet Data_danh_muc
A1: month_id | B1: channel | C1: category | D1: net_sales | E1: returns | F1: units
A2: 201601 | B2: ONLINE | C2: Âm thanh | D2: 7280.92 | E2: 0 | F2: 34
A3: 201601 | B3: ONLINE | C3: Máy ảnh | D3: 9278.78 | E3: 0 | F3: 33
A4: 201601 | B4: ONLINE | C4: Điện thoại | D4: 5930.33 | E4: 538.65 | F4: 41
A5: 201601 | B5: ONLINE | C5: Máy tính | D5: 13054.22 | E5: 0 | F5: 43
A6: 201601 | B6: ONLINE | C6: Game & Đồ chơi | D6: 965.57 | E6: 0 | F6: 35
A7: 201601 | B7: ONLINE | C7: Gia dụng | D7: 5257.3 | E7: 0 | F7: 21
A8: 201601 | B8: ONLINE | C8: Nhạc, phim, sách nói | D8: 7011.23 | E8: 0 | F8: 65
A9: 201601 | B9: ONLINE | C9: TV & Video | D9: 16671.01 | E9: 0 | F9: 27
A10: 201601 | B10: POS | C10: Âm thanh | D10: 19048.07 | E10: 293.66 | F10: 152
A11: 201601 | B11: POS | C11: Máy ảnh | D11: 128457.82 | E11: 1421 | F11: 273
A12: 201601 | B12: POS | C12: Điện thoại | D12: 19704.93 | E12: 23.72 | F12: 110
A13: 201601 | B13: POS | C13: Máy tính | D13: 62463.41 | E13: 238.85 | F13: 224
... A983: 202102 | B983: POS | C983: TV & Video | D983: 28801.95 | E983: 0 | F983: 79

Sheet Calc
A1: Tháng (chọn) | B1: month_id | D1: k | E1: month_id | F1: Tháng | G1: Net Revenue (nghìn USD) | H1: Số đơn | I1: Δ sau quy đổi (nghìn USD) | K1: Danh mục | L1: Net Sales (nghìn USD) | M1: khoá xếp | N1: Danh mục (xếp) | O1: Net Sales (xếp)
A2: 02/2021 | B2: 202102 | D2: 0 | E2: =YEAR(DATE(INT(Dashboard!$D$6/100),MOD(Dashboard!$D$6,100)-23+D2,1))*100+MONTH(DATE(INT(Dashboard!$D$6/100),MOD(Dashboard!$D$6,100)-23+D2,1)) | F2: =RIGHT("0"&MOD(E2,100),2)&"/"&RIGHT(INT(E2/100),2) | G2: =(SUMIFS(Data_thang!$J$2:$J$2974,Data_thang!$A$2:$A$2974,E2,Data_thang!$G$2:$G$2974,Dashboard!$C$6)-SUMIFS(Data_thang!$K$2:$K$2974,Data_thang!$A$2:$A$2974,E2,Data_thang!$G$2:$G$2974,Dashboard!$C$6))/1000 | H2: =SUMIFS(Data_thang!$L$2:$L$2974,Data_thang!$A$2:$A$2974,E2,Data_thang!$G$2:$G$2974,Dashboard!$C$6) | I2: =(SUMIFS(Data_thang!$N$2:$N$2974,Data_thang!$A$2:$A$2974,E2,Data_thang!$G$2:$G$2974,Dashboard!$C$6)-SUMIFS(Data_thang!$O$2:$O$2974,Data_thang!$A$2:$A$2974,E2,Data_thang!$G$2:$G$2974,Dashboard!$C$6)+SUMIFS(Data_thang!$K$2:$K$2974,Data_thang!$A$2:$A$2974,E2,Data_thang!$G$2:$G$2974,Dashboard!$C$6))/1000 | K2: Gia dụng | L2: =SUMIFS(Data_danh_muc!$D$2:$D$983,Data_danh_muc!$A$2:$A$983,Dashboard!$D$6,Data_danh_muc!$B$2:$B$983,Dashboard!$C$6,Data_danh_muc!$C$2:$C$983,K2)/1000 | M2: =L2+ROW()/1000000000 | N2: =INDEX($K$2:$K$9,MATCH(LARGE($M$2:$M$9,ROW()-1),$M$2:$M$9,0)) | O2: =INDEX($L$2:$L$9,MATCH(LARGE($M$2:$M$9,ROW()-1),$M$2:$M$9,0))
A3: 01/2021 | B3: 202101 | D3: 1 | E3: =YEAR(DATE(INT(Dashboard!$D$6/100),MOD(Dashboard!$D$6,100)-23+D3,1))*100+MONTH(DATE(INT(Dashboard!$D$6/100),MOD(Dashboard!$D$6,100)-23+D3,1)) | F3: =RIGHT("0"&MOD(E3,100),2)&"/"&RIGHT(INT(E3/100),2) | G3: =(SUMIFS(Data_thang!$J$2:$J$2974,Data_thang!$A$2:$A$2974,E3,Data_thang!$G$2:$G$2974,Dashboard!$C$6)-SUMIFS(Data_thang!$K$2:$K$2974,Data_thang!$A$2:$A$2974,E3,Data_thang!$G$2:$G$2974,Dashboard!$C$6))/1000 | H3: =SUMIFS(Data_thang!$L$2:$L$2974,Data_thang!$A$2:$A$2974,E3,Data_thang!$G$2:$G$2974,Dashboard!$C$6) | I3: =(SUMIFS(Data_thang!$N$2:$N$2974,Data_thang!$A$2:$A$2974,E3,Data_thang!$G$2:$G$2974,Dashboard!$C$6)-SUMIFS(Data_thang!$O$2:$O$2974,Data_thang!$A$2:$A$2974,E3,Data_thang!$G$2:$G$2974,Dashboard!$C$6)+SUMIFS(Data_thang!$K$2:$K$2974,Data_thang!$A$2:$A$2974,E3,Data_thang!$G$2:$G$2974,Dashboard!$C$6))/1000 | K3: Máy tính | L3: =SUMIFS(Data_danh_muc!$D$2:$D$983,Data_danh_muc!$A$2:$A$983,Dashboard!$D$6,Data_danh_muc!$B$2:$B$983,Dashboard!$C$6,Data_danh_muc!$C$2:$C$983,K3)/1000 | M3: =L3+ROW()/1000000000 | N3: =INDEX($K$2:$K$9,MATCH(LARGE($M$2:$M$9,ROW()-1),$M$2:$M$9,0)) | O3: =INDEX($L$2:$L$9,MATCH(LARGE($M$2:$M$9,ROW()-1),$M$2:$M$9,0))
A4: 12/2020 | B4: 202012 | D4: 2 | E4: =YEAR(DATE(INT(Dashboard!$D$6/100),MOD(Dashboard!$D$6,100)-23+D4,1))*100+MONTH(DATE(INT(Dashboard!$D$6/100),MOD(Dashboard!$D$6,100)-23+D4,1)) | F4: =RIGHT("0"&MOD(E4,100),2)&"/"&RIGHT(INT(E4/100),2) | G4: =(SUMIFS(Data_thang!$J$2:$J$2974,Data_thang!$A$2:$A$2974,E4,Data_thang!$G$2:$G$2974,Dashboard!$C$6)-SUMIFS(Data_thang!$K$2:$K$2974,Data_thang!$A$2:$A$2974,E4,Data_thang!$G$2:$G$2974,Dashboard!$C$6))/1000 | H4: =SUMIFS(Data_thang!$L$2:$L$2974,Data_thang!$A$2:$A$2974,E4,Data_thang!$G$2:$G$2974,Dashboard!$C$6) | I4: =(SUMIFS(Data_thang!$N$2:$N$2974,Data_thang!$A$2:$A$2974,E4,Data_thang!$G$2:$G$2974,Dashboard!$C$6)-SUMIFS(Data_thang!$O$2:$O$2974,Data_thang!$A$2:$A$2974,E4,Data_thang!$G$2:$G$2974,Dashboard!$C$6)+SUMIFS(Data_thang!$K$2:$K$2974,Data_thang!$A$2:$A$2974,E4,Data_thang!$G$2:$G$2974,Dashboard!$C$6))/1000 | K4: Máy ảnh | L4: =SUMIFS(Data_danh_muc!$D$2:$D$983,Data_danh_muc!$A$2:$A$983,Dashboard!$D$6,Data_danh_muc!$B$2:$B$983,Dashboard!$C$6,Data_danh_muc!$C$2:$C$983,K4)/1000 | M4: =L4+ROW()/1000000000 | N4: =INDEX($K$2:$K$9,MATCH(LARGE($M$2:$M$9,ROW()-1),$M$2:$M$9,0)) | O4: =INDEX($L$2:$L$9,MATCH(LARGE($M$2:$M$9,ROW()-1),$M$2:$M$9,0))
A5: 11/2020 | B5: 202011 | D5: 3 | E5: =YEAR(DATE(INT(Dashboard!$D$6/100),MOD(Dashboard!$D$6,100)-23+D5,1))*100+MONTH(DATE(INT(Dashboard!$D$6/100),MOD(Dashboard!$D$6,100)-23+D5,1)) | F5: =RIGHT("0"&MOD(E5,100),2)&"/"&RIGHT(INT(E5/100),2) | G5: =(SUMIFS(Data_thang!$J$2:$J$2974,Data_thang!$A$2:$A$2974,E5,Data_thang!$G$2:$G$2974,Dashboard!$C$6)-SUMIFS(Data_thang!$K$2:$K$2974,Data_thang!$A$2:$A$2974,E5,Data_thang!$G$2:$G$2974,Dashboard!$C$6))/1000 | H5: =SUMIFS(Data_thang!$L$2:$L$2974,Data_thang!$A$2:$A$2974,E5,Data_thang!$G$2:$G$2974,Dashboard!$C$6) | I5: =(SUMIFS(Data_thang!$N$2:$N$2974,Data_thang!$A$2:$A$2974,E5,Data_thang!$G$2:$G$2974,Dashboard!$C$6)-SUMIFS(Data_thang!$O$2:$O$2974,Data_thang!$A$2:$A$2974,E5,Data_thang!$G$2:$G$2974,Dashboard!$C$6)+SUMIFS(Data_thang!$K$2:$K$2974,Data_thang!$A$2:$A$2974,E5,Data_thang!$G$2:$G$2974,Dashboard!$C$6))/1000 | K5: Điện thoại | L5: =SUMIFS(Data_danh_muc!$D$2:$D$983,Data_danh_muc!$A$2:$A$983,Dashboard!$D$6,Data_danh_muc!$B$2:$B$983,Dashboard!$C$6,Data_danh_muc!$C$2:$C$983,K5)/1000 | M5: =L5+ROW()/1000000000 | N5: =INDEX($K$2:$K$9,MATCH(LARGE($M$2:$M$9,ROW()-1),$M$2:$M$9,0)) | O5: =INDEX($L$2:$L$9,MATCH(LARGE($M$2:$M$9,ROW()-1),$M$2:$M$9,0))
A6: 10/2020 | B6: 202010 | D6: 4 | E6: =YEAR(DATE(INT(Dashboard!$D$6/100),MOD(Dashboard!$D$6,100)-23+D6,1))*100+MONTH(DATE(INT(Dashboard!$D$6/100),MOD(Dashboard!$D$6,100)-23+D6,1)) | F6: =RIGHT("0"&MOD(E6,100),2)&"/"&RIGHT(INT(E6/100),2) | G6: =(SUMIFS(Data_thang!$J$2:$J$2974,Data_thang!$A$2:$A$2974,E6,Data_thang!$G$2:$G$2974,Dashboard!$C$6)-SUMIFS(Data_thang!$K$2:$K$2974,Data_thang!$A$2:$A$2974,E6,Data_thang!$G$2:$G$2974,Dashboard!$C$6))/1000 | H6: =SUMIFS(Data_thang!$L$2:$L$2974,Data_thang!$A$2:$A$2974,E6,Data_thang!$G$2:$G$2974,Dashboard!$C$6) | I6: =(SUMIFS(Data_thang!$N$2:$N$2974,Data_thang!$A$2:$A$2974,E6,Data_thang!$G$2:$G$2974,Dashboard!$C$6)-SUMIFS(Data_thang!$O$2:$O$2974,Data_thang!$A$2:$A$2974,E6,Data_thang!$G$2:$G$2974,Dashboard!$C$6)+SUMIFS(Data_thang!$K$2:$K$2974,Data_thang!$A$2:$A$2974,E6,Data_thang!$G$2:$G$2974,Dashboard!$C$6))/1000 | K6: TV & Video | L6: =SUMIFS(Data_danh_muc!$D$2:$D$983,Data_danh_muc!$A$2:$A$983,Dashboard!$D$6,Data_danh_muc!$B$2:$B$983,Dashboard!$C$6,Data_danh_muc!$C$2:$C$983,K6)/1000 | M6: =L6+ROW()/1000000000 | N6: =INDEX($K$2:$K$9,MATCH(LARGE($M$2:$M$9,ROW()-1),$M$2:$M$9,0)) | O6: =INDEX($L$2:$L$9,MATCH(LARGE($M$2:$M$9,ROW()-1),$M$2:$M$9,0))
A7: 09/2020 | B7: 202009 | D7: 5 | E7: =YEAR(DATE(INT(Dashboard!$D$6/100),MOD(Dashboard!$D$6,100)-23+D7,1))*100+MONTH(DATE(INT(Dashboard!$D$6/100),MOD(Dashboard!$D$6,100)-23+D7,1)) | F7: =RIGHT("0"&MOD(E7,100),2)&"/"&RIGHT(INT(E7/100),2) | G7: =(SUMIFS(Data_thang!$J$2:$J$2974,Data_thang!$A$2:$A$2974,E7,Data_thang!$G$2:$G$2974,Dashboard!$C$6)-SUMIFS(Data_thang!$K$2:$K$2974,Data_thang!$A$2:$A$2974,E7,Data_thang!$G$2:$G$2974,Dashboard!$C$6))/1000 | H7: =SUMIFS(Data_thang!$L$2:$L$2974,Data_thang!$A$2:$A$2974,E7,Data_thang!$G$2:$G$2974,Dashboard!$C$6) | I7: =(SUMIFS(Data_thang!$N$2:$N$2974,Data_thang!$A$2:$A$2974,E7,Data_thang!$G$2:$G$2974,Dashboard!$C$6)-SUMIFS(Data_thang!$O$2:$O$2974,Data_thang!$A$2:$A$2974,E7,Data_thang!$G$2:$G$2974,Dashboard!$C$6)+SUMIFS(Data_thang!$K$2:$K$2974,Data_thang!$A$2:$A$2974,E7,Data_thang!$G$2:$G$2974,Dashboard!$C$6))/1000 | K7: Game & Đồ chơi | L7: =SUMIFS(Data_danh_muc!$D$2:$D$983,Data_danh_muc!$A$2:$A$983,Dashboard!$D$6,Data_danh_muc!$B$2:$B$983,Dashboard!$C$6,Data_danh_muc!$C$2:$C$983,K7)/1000 | M7: =L7+ROW()/1000000000 | N7: =INDEX($K$2:$K$9,MATCH(LARGE($M$2:$M$9,ROW()-1),$M$2:$M$9,0)) | O7: =INDEX($L$2:$L$9,MATCH(LARGE($M$2:$M$9,ROW()-1),$M$2:$M$9,0))
A8: 08/2020 | B8: 202008 | D8: 6 | E8: =YEAR(DATE(INT(Dashboard!$D$6/100),MOD(Dashboard!$D$6,100)-23+D8,1))*100+MONTH(DATE(INT(Dashboard!$D$6/100),MOD(Dashboard!$D$6,100)-23+D8,1)) | F8: =RIGHT("0"&MOD(E8,100),2)&"/"&RIGHT(INT(E8/100),2) | G8: =(SUMIFS(Data_thang!$J$2:$J$2974,Data_thang!$A$2:$A$2974,E8,Data_thang!$G$2:$G$2974,Dashboard!$C$6)-SUMIFS(Data_thang!$K$2:$K$2974,Data_thang!$A$2:$A$2974,E8,Data_thang!$G$2:$G$2974,Dashboard!$C$6))/1000 | H8: =SUMIFS(Data_thang!$L$2:$L$2974,Data_thang!$A$2:$A$2974,E8,Data_thang!$G$2:$G$2974,Dashboard!$C$6) | I8: =(SUMIFS(Data_thang!$N$2:$N$2974,Data_thang!$A$2:$A$2974,E8,Data_thang!$G$2:$G$2974,Dashboard!$C$6)-SUMIFS(Data_thang!$O$2:$O$2974,Data_thang!$A$2:$A$2974,E8,Data_thang!$G$2:$G$2974,Dashboard!$C$6)+SUMIFS(Data_thang!$K$2:$K$2974,Data_thang!$A$2:$A$2974,E8,Data_thang!$G$2:$G$2974,Dashboard!$C$6))/1000 | K8: Âm thanh | L8: =SUMIFS(Data_danh_muc!$D$2:$D$983,Data_danh_muc!$A$2:$A$983,Dashboard!$D$6,Data_danh_muc!$B$2:$B$983,Dashboard!$C$6,Data_danh_muc!$C$2:$C$983,K8)/1000 | M8: =L8+ROW()/1000000000 | N8: =INDEX($K$2:$K$9,MATCH(LARGE($M$2:$M$9,ROW()-1),$M$2:$M$9,0)) | O8: =INDEX($L$2:$L$9,MATCH(LARGE($M$2:$M$9,ROW()-1),$M$2:$M$9,0))
A9: 07/2020 | B9: 202007 | D9: 7 | E9: =YEAR(DATE(INT(Dashboard!$D$6/100),MOD(Dashboard!$D$6,100)-23+D9,1))*100+MONTH(DATE(INT(Dashboard!$D$6/100),MOD(Dashboard!$D$6,100)-23+D9,1)) | F9: =RIGHT("0"&MOD(E9,100),2)&"/"&RIGHT(INT(E9/100),2) | G9: =(SUMIFS(Data_thang!$J$2:$J$2974,Data_thang!$A$2:$A$2974,E9,Data_thang!$G$2:$G$2974,Dashboard!$C$6)-SUMIFS(Data_thang!$K$2:$K$2974,Data_thang!$A$2:$A$2974,E9,Data_thang!$G$2:$G$2974,Dashboard!$C$6))/1000 | H9: =SUMIFS(Data_thang!$L$2:$L$2974,Data_thang!$A$2:$A$2974,E9,Data_thang!$G$2:$G$2974,Dashboard!$C$6) | I9: =(SUMIFS(Data_thang!$N$2:$N$2974,Data_thang!$A$2:$A$2974,E9,Data_thang!$G$2:$G$2974,Dashboard!$C$6)-SUMIFS(Data_thang!$O$2:$O$2974,Data_thang!$A$2:$A$2974,E9,Data_thang!$G$2:$G$2974,Dashboard!$C$6)+SUMIFS(Data_thang!$K$2:$K$2974,Data_thang!$A$2:$A$2974,E9,Data_thang!$G$2:$G$2974,Dashboard!$C$6))/1000 | K9: Nhạc, phim, sách nói | L9: =SUMIFS(Data_danh_muc!$D$2:$D$983,Data_danh_muc!$A$2:$A$983,Dashboard!$D$6,Data_danh_muc!$B$2:$B$983,Dashboard!$C$6,Data_danh_muc!$C$2:$C$983,K9)/1000 | M9: =L9+ROW()/1000000000 | N9: =INDEX($K$2:$K$9,MATCH(LARGE($M$2:$M$9,ROW()-1),$M$2:$M$9,0)) | O9: =INDEX($L$2:$L$9,MATCH(LARGE($M$2:$M$9,ROW()-1),$M$2:$M$9,0))
A10: 06/2020 | B10: 202006 | D10: 8 | E10: =YEAR(DATE(INT(Dashboard!$D$6/100),MOD(Dashboard!$D$6,100)-23+D10,1))*100+MONTH(DATE(INT(Dashboard!$D$6/100),MOD(Dashboard!$D$6,100)-23+D10,1)) | F10: =RIGHT("0"&MOD(E10,100),2)&"/"&RIGHT(INT(E10/100),2) | G10: =(SUMIFS(Data_thang!$J$2:$J$2974,Data_thang!$A$2:$A$2974,E10,Data_thang!$G$2:$G$2974,Dashboard!$C$6)-SUMIFS(Data_thang!$K$2:$K$2974,Data_thang!$A$2:$A$2974,E10,Data_thang!$G$2:$G$2974,Dashboard!$C$6))/1000 | H10: =SUMIFS(Data_thang!$L$2:$L$2974,Data_thang!$A$2:$A$2974,E10,Data_thang!$G$2:$G$2974,Dashboard!$C$6) | I10: =(SUMIFS(Data_thang!$N$2:$N$2974,Data_thang!$A$2:$A$2974,E10,Data_thang!$G$2:$G$2974,Dashboard!$C$6)-SUMIFS(Data_thang!$O$2:$O$2974,Data_thang!$A$2:$A$2974,E10,Data_thang!$G$2:$G$2974,Dashboard!$C$6)+SUMIFS(Data_thang!$K$2:$K$2974,Data_thang!$A$2:$A$2974,E10,Data_thang!$G$2:$G$2974,Dashboard!$C$6))/1000
A11: 05/2020 | B11: 202005 | D11: 9 | E11: =YEAR(DATE(INT(Dashboard!$D$6/100),MOD(Dashboard!$D$6,100)-23+D11,1))*100+MONTH(DATE(INT(Dashboard!$D$6/100),MOD(Dashboard!$D$6,100)-23+D11,1)) | F11: =RIGHT("0"&MOD(E11,100),2)&"/"&RIGHT(INT(E11/100),2) | G11: =(SUMIFS(Data_thang!$J$2:$J$2974,Data_thang!$A$2:$A$2974,E11,Data_thang!$G$2:$G$2974,Dashboard!$C$6)-SUMIFS(Data_thang!$K$2:$K$2974,Data_thang!$A$2:$A$2974,E11,Data_thang!$G$2:$G$2974,Dashboard!$C$6))/1000 | H11: =SUMIFS(Data_thang!$L$2:$L$2974,Data_thang!$A$2:$A$2974,E11,Data_thang!$G$2:$G$2974,Dashboard!$C$6) | I11: =(SUMIFS(Data_thang!$N$2:$N$2974,Data_thang!$A$2:$A$2974,E11,Data_thang!$G$2:$G$2974,Dashboard!$C$6)-SUMIFS(Data_thang!$O$2:$O$2974,Data_thang!$A$2:$A$2974,E11,Data_thang!$G$2:$G$2974,Dashboard!$C$6)+SUMIFS(Data_thang!$K$2:$K$2974,Data_thang!$A$2:$A$2974,E11,Data_thang!$G$2:$G$2974,Dashboard!$C$6))/1000
A12: 04/2020 | B12: 202004 | D12: 10 | E12: =YEAR(DATE(INT(Dashboard!$D$6/100),MOD(Dashboard!$D$6,100)-23+D12,1))*100+MONTH(DATE(INT(Dashboard!$D$6/100),MOD(Dashboard!$D$6,100)-23+D12,1)) | F12: =RIGHT("0"&MOD(E12,100),2)&"/"&RIGHT(INT(E12/100),2) | G12: =(SUMIFS(Data_thang!$J$2:$J$2974,Data_thang!$A$2:$A$2974,E12,Data_thang!$G$2:$G$2974,Dashboard!$C$6)-SUMIFS(Data_thang!$K$2:$K$2974,Data_thang!$A$2:$A$2974,E12,Data_thang!$G$2:$G$2974,Dashboard!$C$6))/1000 | H12: =SUMIFS(Data_thang!$L$2:$L$2974,Data_thang!$A$2:$A$2974,E12,Data_thang!$G$2:$G$2974,Dashboard!$C$6) | I12: =(SUMIFS(Data_thang!$N$2:$N$2974,Data_thang!$A$2:$A$2974,E12,Data_thang!$G$2:$G$2974,Dashboard!$C$6)-SUMIFS(Data_thang!$O$2:$O$2974,Data_thang!$A$2:$A$2974,E12,Data_thang!$G$2:$G$2974,Dashboard!$C$6)+SUMIFS(Data_thang!$K$2:$K$2974,Data_thang!$A$2:$A$2974,E12,Data_thang!$G$2:$G$2974,Dashboard!$C$6))/1000
A13: 03/2020 | B13: 202003 | D13: 11 | E13: =YEAR(DATE(INT(Dashboard!$D$6/100),MOD(Dashboard!$D$6,100)-23+D13,1))*100+MONTH(DATE(INT(Dashboard!$D$6/100),MOD(Dashboard!$D$6,100)-23+D13,1)) | F13: =RIGHT("0"&MOD(E13,100),2)&"/"&RIGHT(INT(E13/100),2) | G13: =(SUMIFS(Data_thang!$J$2:$J$2974,Data_thang!$A$2:$A$2974,E13,Data_thang!$G$2:$G$2974,Dashboard!$C$6)-SUMIFS(Data_thang!$K$2:$K$2974,Data_thang!$A$2:$A$2974,E13,Data_thang!$G$2:$G$2974,Dashboard!$C$6))/1000 | H13: =SUMIFS(Data_thang!$L$2:$L$2974,Data_thang!$A$2:$A$2974,E13,Data_thang!$G$2:$G$2974,Dashboard!$C$6) | I13: =(SUMIFS(Data_thang!$N$2:$N$2974,Data_thang!$A$2:$A$2974,E13,Data_thang!$G$2:$G$2974,Dashboard!$C$6)-SUMIFS(Data_thang!$O$2:$O$2974,Data_thang!$A$2:$A$2974,E13,Data_thang!$G$2:$G$2974,Dashboard!$C$6)+SUMIFS(Data_thang!$K$2:$K$2974,Data_thang!$A$2:$A$2974,E13,Data_thang!$G$2:$G$2974,Dashboard!$C$6))/1000
A14: 02/2020 | B14: 202002 | D14: 12 | E14: =YEAR(DATE(INT(Dashboard!$D$6/100),MOD(Dashboard!$D$6,100)-23+D14,1))*100+MONTH(DATE(INT(Dashboard!$D$6/100),MOD(Dashboard!$D$6,100)-23+D14,1)) | F14: =RIGHT("0"&MOD(E14,100),2)&"/"&RIGHT(INT(E14/100),2) | G14: =(SUMIFS(Data_thang!$J$2:$J$2974,Data_thang!$A$2:$A$2974,E14,Data_thang!$G$2:$G$2974,Dashboard!$C$6)-SUMIFS(Data_thang!$K$2:$K$2974,Data_thang!$A$2:$A$2974,E14,Data_thang!$G$2:$G$2974,Dashboard!$C$6))/1000 | H14: =SUMIFS(Data_thang!$L$2:$L$2974,Data_thang!$A$2:$A$2974,E14,Data_thang!$G$2:$G$2974,Dashboard!$C$6) | I14: =(SUMIFS(Data_thang!$N$2:$N$2974,Data_thang!$A$2:$A$2974,E14,Data_thang!$G$2:$G$2974,Dashboard!$C$6)-SUMIFS(Data_thang!$O$2:$O$2974,Data_thang!$A$2:$A$2974,E14,Data_thang!$G$2:$G$2974,Dashboard!$C$6)+SUMIFS(Data_thang!$K$2:$K$2974,Data_thang!$A$2:$A$2974,E14,Data_thang!$G$2:$G$2974,Dashboard!$C$6))/1000
A15: 01/2020 | B15: 202001 | D15: 13 | E15: =YEAR(DATE(INT(Dashboard!$D$6/100),MOD(Dashboard!$D$6,100)-23+D15,1))*100+MONTH(DATE(INT(Dashboard!$D$6/100),MOD(Dashboard!$D$6,100)-23+D15,1)) | F15: =RIGHT("0"&MOD(E15,100),2)&"/"&RIGHT(INT(E15/100),2) | G15: =(SUMIFS(Data_thang!$J$2:$J$2974,Data_thang!$A$2:$A$2974,E15,Data_thang!$G$2:$G$2974,Dashboard!$C$6)-SUMIFS(Data_thang!$K$2:$K$2974,Data_thang!$A$2:$A$2974,E15,Data_thang!$G$2:$G$2974,Dashboard!$C$6))/1000 | H15: =SUMIFS(Data_thang!$L$2:$L$2974,Data_thang!$A$2:$A$2974,E15,Data_thang!$G$2:$G$2974,Dashboard!$C$6) | I15: =(SUMIFS(Data_thang!$N$2:$N$2974,Data_thang!$A$2:$A$2974,E15,Data_thang!$G$2:$G$2974,Dashboard!$C$6)-SUMIFS(Data_thang!$O$2:$O$2974,Data_thang!$A$2:$A$2974,E15,Data_thang!$G$2:$G$2974,Dashboard!$C$6)+SUMIFS(Data_thang!$K$2:$K$2974,Data_thang!$A$2:$A$2974,E15,Data_thang!$G$2:$G$2974,Dashboard!$C$6))/1000
A16: 12/2019 | B16: 201912 | D16: 14 | E16: =YEAR(DATE(INT(Dashboard!$D$6/100),MOD(Dashboard!$D$6,100)-23+D16,1))*100+MONTH(DATE(INT(Dashboard!$D$6/100),MOD(Dashboard!$D$6,100)-23+D16,1)) | F16: =RIGHT("0"&MOD(E16,100),2)&"/"&RIGHT(INT(E16/100),2) | G16: =(SUMIFS(Data_thang!$J$2:$J$2974,Data_thang!$A$2:$A$2974,E16,Data_thang!$G$2:$G$2974,Dashboard!$C$6)-SUMIFS(Data_thang!$K$2:$K$2974,Data_thang!$A$2:$A$2974,E16,Data_thang!$G$2:$G$2974,Dashboard!$C$6))/1000 | H16: =SUMIFS(Data_thang!$L$2:$L$2974,Data_thang!$A$2:$A$2974,E16,Data_thang!$G$2:$G$2974,Dashboard!$C$6) | I16: =(SUMIFS(Data_thang!$N$2:$N$2974,Data_thang!$A$2:$A$2974,E16,Data_thang!$G$2:$G$2974,Dashboard!$C$6)-SUMIFS(Data_thang!$O$2:$O$2974,Data_thang!$A$2:$A$2974,E16,Data_thang!$G$2:$G$2974,Dashboard!$C$6)+SUMIFS(Data_thang!$K$2:$K$2974,Data_thang!$A$2:$A$2974,E16,Data_thang!$G$2:$G$2974,Dashboard!$C$6))/1000
A17: 11/2019 | B17: 201911 | D17: 15 | E17: =YEAR(DATE(INT(Dashboard!$D$6/100),MOD(Dashboard!$D$6,100)-23+D17,1))*100+MONTH(DATE(INT(Dashboard!$D$6/100),MOD(Dashboard!$D$6,100)-23+D17,1)) | F17: =RIGHT("0"&MOD(E17,100),2)&"/"&RIGHT(INT(E17/100),2) | G17: =(SUMIFS(Data_thang!$J$2:$J$2974,Data_thang!$A$2:$A$2974,E17,Data_thang!$G$2:$G$2974,Dashboard!$C$6)-SUMIFS(Data_thang!$K$2:$K$2974,Data_thang!$A$2:$A$2974,E17,Data_thang!$G$2:$G$2974,Dashboard!$C$6))/1000 | H17: =SUMIFS(Data_thang!$L$2:$L$2974,Data_thang!$A$2:$A$2974,E17,Data_thang!$G$2:$G$2974,Dashboard!$C$6) | I17: =(SUMIFS(Data_thang!$N$2:$N$2974,Data_thang!$A$2:$A$2974,E17,Data_thang!$G$2:$G$2974,Dashboard!$C$6)-SUMIFS(Data_thang!$O$2:$O$2974,Data_thang!$A$2:$A$2974,E17,Data_thang!$G$2:$G$2974,Dashboard!$C$6)+SUMIFS(Data_thang!$K$2:$K$2974,Data_thang!$A$2:$A$2974,E17,Data_thang!$G$2:$G$2974,Dashboard!$C$6))/1000
A18: 10/2019 | B18: 201910 | D18: 16 | E18: =YEAR(DATE(INT(Dashboard!$D$6/100),MOD(Dashboard!$D$6,100)-23+D18,1))*100+MONTH(DATE(INT(Dashboard!$D$6/100),MOD(Dashboard!$D$6,100)-23+D18,1)) | F18: =RIGHT("0"&MOD(E18,100),2)&"/"&RIGHT(INT(E18/100),2) | G18: =(SUMIFS(Data_thang!$J$2:$J$2974,Data_thang!$A$2:$A$2974,E18,Data_thang!$G$2:$G$2974,Dashboard!$C$6)-SUMIFS(Data_thang!$K$2:$K$2974,Data_thang!$A$2:$A$2974,E18,Data_thang!$G$2:$G$2974,Dashboard!$C$6))/1000 | H18: =SUMIFS(Data_thang!$L$2:$L$2974,Data_thang!$A$2:$A$2974,E18,Data_thang!$G$2:$G$2974,Dashboard!$C$6) | I18: =(SUMIFS(Data_thang!$N$2:$N$2974,Data_thang!$A$2:$A$2974,E18,Data_thang!$G$2:$G$2974,Dashboard!$C$6)-SUMIFS(Data_thang!$O$2:$O$2974,Data_thang!$A$2:$A$2974,E18,Data_thang!$G$2:$G$2974,Dashboard!$C$6)+SUMIFS(Data_thang!$K$2:$K$2974,Data_thang!$A$2:$A$2974,E18,Data_thang!$G$2:$G$2974,Dashboard!$C$6))/1000
A19: 09/2019 | B19: 201909 | D19: 17 | E19: =YEAR(DATE(INT(Dashboard!$D$6/100),MOD(Dashboard!$D$6,100)-23+D19,1))*100+MONTH(DATE(INT(Dashboard!$D$6/100),MOD(Dashboard!$D$6,100)-23+D19,1)) | F19: =RIGHT("0"&MOD(E19,100),2)&"/"&RIGHT(INT(E19/100),2) | G19: =(SUMIFS(Data_thang!$J$2:$J$2974,Data_thang!$A$2:$A$2974,E19,Data_thang!$G$2:$G$2974,Dashboard!$C$6)-SUMIFS(Data_thang!$K$2:$K$2974,Data_thang!$A$2:$A$2974,E19,Data_thang!$G$2:$G$2974,Dashboard!$C$6))/1000 | H19: =SUMIFS(Data_thang!$L$2:$L$2974,Data_thang!$A$2:$A$2974,E19,Data_thang!$G$2:$G$2974,Dashboard!$C$6) | I19: =(SUMIFS(Data_thang!$N$2:$N$2974,Data_thang!$A$2:$A$2974,E19,Data_thang!$G$2:$G$2974,Dashboard!$C$6)-SUMIFS(Data_thang!$O$2:$O$2974,Data_thang!$A$2:$A$2974,E19,Data_thang!$G$2:$G$2974,Dashboard!$C$6)+SUMIFS(Data_thang!$K$2:$K$2974,Data_thang!$A$2:$A$2974,E19,Data_thang!$G$2:$G$2974,Dashboard!$C$6))/1000
A20: 08/2019 | B20: 201908 | D20: 18 | E20: =YEAR(DATE(INT(Dashboard!$D$6/100),MOD(Dashboard!$D$6,100)-23+D20,1))*100+MONTH(DATE(INT(Dashboard!$D$6/100),MOD(Dashboard!$D$6,100)-23+D20,1)) | F20: =RIGHT("0"&MOD(E20,100),2)&"/"&RIGHT(INT(E20/100),2) | G20: =(SUMIFS(Data_thang!$J$2:$J$2974,Data_thang!$A$2:$A$2974,E20,Data_thang!$G$2:$G$2974,Dashboard!$C$6)-SUMIFS(Data_thang!$K$2:$K$2974,Data_thang!$A$2:$A$2974,E20,Data_thang!$G$2:$G$2974,Dashboard!$C$6))/1000 | H20: =SUMIFS(Data_thang!$L$2:$L$2974,Data_thang!$A$2:$A$2974,E20,Data_thang!$G$2:$G$2974,Dashboard!$C$6) | I20: =(SUMIFS(Data_thang!$N$2:$N$2974,Data_thang!$A$2:$A$2974,E20,Data_thang!$G$2:$G$2974,Dashboard!$C$6)-SUMIFS(Data_thang!$O$2:$O$2974,Data_thang!$A$2:$A$2974,E20,Data_thang!$G$2:$G$2974,Dashboard!$C$6)+SUMIFS(Data_thang!$K$2:$K$2974,Data_thang!$A$2:$A$2974,E20,Data_thang!$G$2:$G$2974,Dashboard!$C$6))/1000
A21: 07/2019 | B21: 201907 | D21: 19 | E21: =YEAR(DATE(INT(Dashboard!$D$6/100),MOD(Dashboard!$D$6,100)-23+D21,1))*100+MONTH(DATE(INT(Dashboard!$D$6/100),MOD(Dashboard!$D$6,100)-23+D21,1)) | F21: =RIGHT("0"&MOD(E21,100),2)&"/"&RIGHT(INT(E21/100),2) | G21: =(SUMIFS(Data_thang!$J$2:$J$2974,Data_thang!$A$2:$A$2974,E21,Data_thang!$G$2:$G$2974,Dashboard!$C$6)-SUMIFS(Data_thang!$K$2:$K$2974,Data_thang!$A$2:$A$2974,E21,Data_thang!$G$2:$G$2974,Dashboard!$C$6))/1000 | H21: =SUMIFS(Data_thang!$L$2:$L$2974,Data_thang!$A$2:$A$2974,E21,Data_thang!$G$2:$G$2974,Dashboard!$C$6) | I21: =(SUMIFS(Data_thang!$N$2:$N$2974,Data_thang!$A$2:$A$2974,E21,Data_thang!$G$2:$G$2974,Dashboard!$C$6)-SUMIFS(Data_thang!$O$2:$O$2974,Data_thang!$A$2:$A$2974,E21,Data_thang!$G$2:$G$2974,Dashboard!$C$6)+SUMIFS(Data_thang!$K$2:$K$2974,Data_thang!$A$2:$A$2974,E21,Data_thang!$G$2:$G$2974,Dashboard!$C$6))/1000
... A25: 03/2019 | B25: 201903 | D25: 23 | E25: =YEAR(DATE(INT(Dashboard!$D$6/100),MOD(Dashboard!$D$6,100)-23+D25,1))*100+MONTH(DATE(INT(Dashboard!$D$6/100),MOD(Dashboard!$D$6,100)-23+D25,1)) | F25: =RIGHT("0"&MOD(E25,100),2)&"/"&RIGHT(INT(E25/100),2) | G25: =(SUMIFS(Data_thang!$J$2:$J$2974,Data_thang!$A$2:$A$2974,E25,Data_thang!$G$2:$G$2974,Dashboard!$C$6)-SUMIFS(Data_thang!$K$2:$K$2974,Data_thang!$A$2:$A$2974,E25,Data_thang!$G$2:$G$2974,Dashboard!$C$6))/1000 | H25: =SUMIFS(Data_thang!$L$2:$L$2974,Data_thang!$A$2:$A$2974,E25,Data_thang!$G$2:$G$2974,Dashboard!$C$6) | I25: =(SUMIFS(Data_thang!$N$2:$N$2974,Data_thang!$A$2:$A$2974,E25,Data_thang!$G$2:$G$2974,Dashboard!$C$6)-SUMIFS(Data_thang!$O$2:$O$2974,Data_thang!$A$2:$A$2974,E25,Data_thang!$G$2:$G$2974,Dashboard!$C$6)+SUMIFS(Data_thang!$K$2:$K$2974,Data_thang!$A$2:$A$2974,E25,Data_thang!$G$2:$G$2974,Dashboard!$C$6))/1000
A26: 02/2019 | B26: 201902
A27: 01/2019 | B27: 201901
A28: 12/2018 | B28: 201812
A29: 11/2018 | B29: 201811
A30: Sheet tính toán phụ cho Dashboard — không sửa. | B30: 201810
A31: 09/2018 | B31: 201809
A32: 08/2018 | B32: 201808
A33: 07/2018 | B33: 201807
A34: 06/2018 | B34: 201806
A35: 05/2018 | B35: 201805
A36: 04/2018 | B36: 201804
A37: 03/2018 | B37: 201803
... A63: 01/2016 | B63: 201601

Sheet Huong_dan
A1: Mục | B1: Nội dung
A2: Mục đích | B2: Dashboard Excel một trang cho Sales Manager và Finance: tháng này bán được bao nhiêu, vì sao tăng/giảm, và số của dữ liệu đơn lệch Finance ở đâu.
A3: Cách dùng | B3: Ở sheet Dashboard, chọn Tháng báo cáo và Kênh bán trong 2 ô màu vàng. KPI, câu 'Điểm chính', tiêu đề biểu đồ và bảng cửa hàng vượt ngưỡng tự cập nhật. Sheet Doi_soat lọc được theo tháng, cửa hàng, cờ.
A4: Định nghĩa | B4: Net Sales = Gross Sales − Giảm giá; Net Revenue = Net Sales − Hoàn trả (theo ngày trả hàng); AOV = Net Sales / số đơn; Δ = Finance − dữ liệu đơn; Δ sau quy đổi = online tính theo ngày giao.
A5: Ngưỡng | B5: Ô tháng × cửa hàng vượt ngưỡng khi |Δ| > 200 USD và |Δ %| > 1% (sửa ở Dashboard!G6, H6 nếu Finance đổi quy định).
A6: Nguồn | B6: Data_thang và Data_danh_muc tổng hợp từ Nexa_Sales_P1_Dataset.xlsx và finance_revenue.xlsx bằng _mentor/build_dashboard_xlsx.py (chỉ đơn COMPLETED, đã loại dòng trùng). Không gồm bút toán HQ-ADJ.
A7: Trình bày | B7: Theo Storytelling with Data: mỗi biểu đồ có tiêu đề nêu kết luận; màu xám cho bối cảnh, xanh dương cho điều cần nhìn, đỏ chỉ cho chênh lệch vượt ngưỡng; bỏ lưới và khung thừa; nguồn và ngày dữ liệu ở đầu trang.
A8: Giới hạn | B8: Dashboard Excel lọc theo kênh, chưa lọc theo quốc gia (xem bản HTML hoặc tự thêm cột vào SUMIFS). Excel cần bật tính toán tự động (Formulas → Calculation Options → Automatic).
